pollination/utci_comfort_map/__init__.py
pollination/utci_comfort_map/_comfort.py
pollination/utci_comfort_map/_dynshade.py
pollination/utci_comfort_map/_energy.py
pollination/utci_comfort_map/_prepare_folder.py
pollination/utci_comfort_map/_radiance.py
pollination/utci_comfort_map/_shdcontrib.py
pollination/utci_comfort_map/_view_factor.py
pollination/utci_comfort_map/_view_factor_contribution.py
pollination/utci_comfort_map/entry.py
pollination_utci_comfort_map-0.9.21.dist-info/LICENSE
pollination_utci_comfort_map-0.9.21.dist-info/METADATA
pollination_utci_comfort_map-0.9.21.dist-info/WHEEL
pollination_utci_comfort_map-0.9.21.dist-info/top_level.txt
pollination_utci_comfort_map-0.9.21.dist-info/RECORD
